certbot_dns_alwaysdata/__init__.py
certbot_dns_alwaysdata/dns_alwaysdata.py
certbot_dns_alwaysdata/dns_alwaysdata_test.py
certbot_dns_alwaysdata/testdata/domain.json
certbot_dns_alwaysdata/testdata/record.json
certbot_dns_alwaysdata-0.27.1.dist-info/LICENSE.txt
certbot_dns_alwaysdata-0.27.1.dist-info/METADATA
certbot_dns_alwaysdata-0.27.1.dist-info/WHEEL
certbot_dns_alwaysdata-0.27.1.dist-info/entry_points.txt
certbot_dns_alwaysdata-0.27.1.dist-info/top_level.txt
certbot_dns_alwaysdata-0.27.1.dist-info/RECORD
