Metadata-Version: 2.1
Name: certbot-dns-alwaysdata
Version: 0.27.1
Summary: Alwaysdata DNS Authenticator plugin for Certbot
Home-page: https://github.com/certbot/certbot
Author: Certbot Project
Author-email: client-dev@letsencrypt.org
License: Apache License 2.0
Platform: UNKNOWN
Classifier: Development Status :: 3 - Alpha
Classifier: Environment :: Plugins
Classifier: Intended Audience :: System Administrators
Classifier: License :: OSI Approved :: Apache Software License
Classifier: Operating System :: POSIX :: Linux
Classifier: Programming Language :: Python
Classifier: Programming Language :: Python :: 2
Classifier: Programming Language :: Python :: 2.7
Classifier: Programming Language :: Python :: 3
Classifier: Programming Language :: Python :: 3.4
Classifier: Programming Language :: Python :: 3.5
Classifier: Programming Language :: Python :: 3.6
Classifier: Programming Language :: Python :: 3.7
Classifier: Topic :: Internet :: WWW/HTTP
Classifier: Topic :: Security
Classifier: Topic :: System :: Installation/Setup
Classifier: Topic :: System :: Networking
Classifier: Topic :: System :: Systems Administration
Classifier: Topic :: Utilities
Requires-Python: >=2.7, !=3.0.*, !=3.1.*, !=3.2.*, !=3.3.*
Requires-Dist: acme (>=0.21.1)
Requires-Dist: certbot (>=0.21.1)
Requires-Dist: mock
Requires-Dist: requests (>=2.4.2)
Requires-Dist: setuptools
Requires-Dist: zope.interface
Provides-Extra: docs
Requires-Dist: Sphinx (>=1.0); extra == 'docs'
Requires-Dist: sphinx-rtd-theme; extra == 'docs'
